Metadata-Version: 1.1
Name: pandas-drf-tools
Version: 0.1.0
Summary: A set of tools to make Pandas easy to use with Django REST Framework projects
Home-page: https://github.com/abarto/pandas-drf-tools
Author: Agustin Barto
Author-email: abarto@gmail.com
License: BSD
Keywords: pandas djangorestframework django
Platform: UNKNOWN
Classifier: Development Status :: 3 - Alpha
Classifier: Intended Audience :: Developers
Classifier: Topic :: Software Development :: Libraries
Classifier: License :: OSI Approved :: MIT License
Classifier: Programming Language :: Python :: 3
Classifier: Programming Language :: Python :: 3.3
Classifier: Programming Language :: Python :: 3.4
Classifier: Programming Language :: Python :: 3.5
